pyinthesky/__init__.py
pyinthesky/base.py
pyinthesky/main.py
pyinthesky/meta.py
pyinthesky/methods.py
pyinthesky/minisoap.py
pyinthesky/miniupnp.py
pyinthesky/transport.py
pyinthesky/utils.py
pyinthesky/validators.py
pyinthesky/xmlutils.py
pyinthesky-0.5.dist-info/DESCRIPTION.rst
pyinthesky-0.5.dist-info/METADATA
pyinthesky-0.5.dist-info/RECORD
pyinthesky-0.5.dist-info/WHEEL
pyinthesky-0.5.dist-info/metadata.json
pyinthesky-0.5.dist-info/namespace_packages.txt
pyinthesky-0.5.dist-info/top_level.txt
