Metadata-Version: 2.0
Name: pyinthesky
Version: 0.5
Summary: Python library to interact with Sky boxes.
Home-page: https://github.com/the-allanc/pyinthesky/
Author: Allan Crooks
Author-email: allan@increment.one
License: MIT
Platform: UNKNOWN
Classifier: Development Status :: 4 - Beta
Classifier: Intended Audience :: Developers
Classifier: License :: OSI Approved :: MIT License
Classifier: Operating System :: OS Independent
Classifier: Programming Language :: Python :: 2.7
Classifier: Programming Language :: Python :: 3
Classifier: Topic :: Software Development :: Libraries
Classifier: Topic :: Software Development :: Libraries :: Python Modules
Requires-Python: >=2.7
Requires-Dist: formencode
Requires-Dist: greyupnp
Requires-Dist: iso8601
Requires-Dist: requests
Requires-Dist: six
Provides-Extra: docs
Requires-Dist: allanc-sphinx[yeen] (>=0.2); extra == 'docs'
Requires-Dist: collective.checkdocs; extra == 'docs'
Requires-Dist: jaraco.packaging (>=3.2); extra == 'docs'
Requires-Dist: rst.linker (>=1.9); extra == 'docs'
Requires-Dist: sphinx; extra == 'docs'
Provides-Extra: testing
Requires-Dist: pytest (>=2.8); extra == 'testing'
Requires-Dist: pytest-sugar; extra == 'testing'
